mimicx/__init__.py
mimicx/main.py
mimicx-0.1.86.dist-info/LICENSE
mimicx-0.1.86.dist-info/METADATA
mimicx-0.1.86.dist-info/WHEEL
mimicx-0.1.86.dist-info/top_level.txt
mimicx-0.1.86.dist-info/RECORD
