Metadata-Version: 2.1
Name: mimicx
Version: 0.1.86
Summary: Human-like AI for everyone — vision, text, voice, and more in one simple package.
Home-page: https://github.com/Mimicx-AI/pip-package
Author: MimicX AI
Author-email: mimicx@speedpresta.com
License: MIT
Platform: UNKNOWN
Classifier: Programming Language :: Python :: 3
Classifier: Operating System :: OS Independent
Classifier: License :: OSI Approved :: MIT License
Requires-Python: >=3.9
License-File: LICENSE
